comfydock_cli/__init__.py
comfydock_cli/__main__.py
comfydock_cli/cli.py
comfydock_cli/cli_utils.py
comfydock_cli/completers.py
comfydock_cli/completion_commands.py
comfydock_cli/env_commands.py
comfydock_cli/global_commands.py
comfydock_cli/resolution_strategies.py
comfydock_cli/formatters/__init__.py
comfydock_cli/formatters/error_formatter.py
comfydock_cli/interactive/__init__.py
comfydock_cli/logging/compressed_handler.py
comfydock_cli/logging/environment_logger.py
comfydock_cli/logging/log_compressor.py
comfydock_cli/logging/logging_config.py
comfydock_cli/strategies/__init__.py
comfydock_cli/strategies/interactive.py
comfydock_cli/strategies/rollback.py
comfydock_cli/utils/__init__.py
comfydock_cli/utils/civitai_errors.py
comfydock_cli/utils/pagination.py
comfydock_cli/utils/progress.py
comfydock_cli-1.0.11.dist-info/METADATA
comfydock_cli-1.0.11.dist-info/WHEEL
comfydock_cli-1.0.11.dist-info/entry_points.txt
comfydock_cli-1.0.11.dist-info/licenses/LICENSE.txt
comfydock_cli-1.0.11.dist-info/RECORD
