Metadata-Version: 2.4
Name: comfydock_cli
Version: 1.0.11
Summary: ComfyDock CLI
License-File: LICENSE.txt
Requires-Python: >=3.10
Requires-Dist: argcomplete>=3.5.0
Requires-Dist: comfydock-core>=1.0.11
